wxpay_mcp/__init__.py
wxpay_mcp/server.py
wxpay_mcp/sign_utils.py
wxpay_mcp_python-0.1.2.dist-info/METADATA
wxpay_mcp_python-0.1.2.dist-info/WHEEL
wxpay_mcp_python-0.1.2.dist-info/entry_points.txt
wxpay_mcp_python-0.1.2.dist-info/top_level.txt
wxpay_mcp_python-0.1.2.dist-info/RECORD
