Metadata-Version: 2.4
Name: wxpay-mcp-python
Version: 0.1.2
Summary: 微信支付 MCP 工具包，提供微信支付 JSAPI 支付和订单查询功能的 MCP 实现
Requires-Python: >=3.11
Requires-Dist: cryptography>=44.0.2
Requires-Dist: mcp[cli]>=1.6.0
Requires-Dist: requests>=2.32.3
Requires-Dist: python-dotenv>=1.0.0
